Kimino/__init__.py
Kimino/main.py
Kimino/style.tcss
Kimino/components/BashFile_app.py
Kimino/components/TUI_app.py
Kimino/components/Web_app.py
Kimino/components/__init__.py
kimino-1.0.0.dist-info/licenses/LICENSE
kimino-1.0.0.dist-info/METADATA
kimino-1.0.0.dist-info/WHEEL
kimino-1.0.0.dist-info/entry_points.txt
kimino-1.0.0.dist-info/top_level.txt
kimino-1.0.0.dist-info/RECORD
