Metadata-Version: 2.4
Name: kimino
Version: 1.0.0
Summary: Easy-to-use Linux desktop app entry creator TUI app.
Author-email: Ahum Maitra <theahummaitra@gmail.com>
License-Expression: GPL-3.0-or-later
Requires-Python: >=3.14
License-File: LICENSE
Requires-Dist: textual[syntax]>=6.6.0
Requires-Dist: textual-dev>=1.8.0
Dynamic: license-file
